<annotation>
	<folder>data10</folder>
	<filename>DJI_03873_012.tif</filename>
	<path>C:\Users\pyada\OneDrive - Texas A&amp;M University\Ph.D\TAMUCottonV3\sample1_320_320\data10\DJI_03873_012.tif</path>
	<source>
		<database>Unknown</database>
	</source>
	<size>
		<width>320</width>
		<height>320</height>
		<depth>3</depth>
	</size>
	<segmented>0</segmented>
	<object>
		<name>vc</name>
		<pose>Unspecified</pose>
		<truncated>0</truncated>
		<difficult>0</difficult>
		<bndbox>
			<xmin>149</xmin>
			<ymin>106</ymin>
			<xmax>161</xmax>
			<ymax>117</ymax>
		</bndbox>
	</object>
	<object>
		<name>vc</name>
		<pose>Unspecified</pose>
		<truncated>0</truncated>
		<difficult>0</difficult>
		<bndbox>
			<xmin>148</xmin>
			<ymin>136</ymin>
			<xmax>157</xmax>
			<ymax>148</ymax>
		</bndbox>
	</object>
	<object>
		<name>vc</name>
		<pose>Unspecified</pose>
		<truncated>0</truncated>
		<difficult>0</difficult>
		<bndbox>
			<xmin>146</xmin>
			<ymin>201</ymin>
			<xmax>157</xmax>
			<ymax>213</ymax>
		</bndbox>
	</object>
	<object>
		<name>vc</name>
		<pose>Unspecified</pose>
		<truncated>0</truncated>
		<difficult>0</difficult>
		<bndbox>
			<xmin>142</xmin>
			<ymin>247</ymin>
			<xmax>155</xmax>
			<ymax>260</ymax>
		</bndbox>
	</object>
	<object>
		<name>vc</name>
		<pose>Unspecified</pose>
		<truncated>0</truncated>
		<difficult>0</difficult>
		<bndbox>
			<xmin>305</xmin>
			<ymin>133</ymin>
			<xmax>317</xmax>
			<ymax>152</ymax>
		</bndbox>
	</object>
	<object>
		<name>vc</name>
		<pose>Unspecified</pose>
		<truncated>0</truncated>
		<difficult>0</difficult>
		<bndbox>
			<xmin>301</xmin>
			<ymin>172</ymin>
			<xmax>316</xmax>
			<ymax>196</ymax>
		</bndbox>
	</object>
	<object>
		<name>vc</name>
		<pose>Unspecified</pose>
		<truncated>0</truncated>
		<difficult>0</difficult>
		<bndbox>
			<xmin>301</xmin>
			<ymin>226</ymin>
			<xmax>314</xmax>
			<ymax>239</ymax>
		</bndbox>
	</object>
	<object>
		<name>vc</name>
		<pose>Unspecified</pose>
		<truncated>0</truncated>
		<difficult>0</difficult>
		<bndbox>
			<xmin>299</xmin>
			<ymin>245</ymin>
			<xmax>313</xmax>
			<ymax>255</ymax>
		</bndbox>
	</object>
	<object>
		<name>vc</name>
		<pose>Unspecified</pose>
		<truncated>0</truncated>
		<difficult>0</difficult>
		<bndbox>
			<xmin>297</xmin>
			<ymin>307</ymin>
			<xmax>312</xmax>
			<ymax>319</ymax>
		</bndbox>
	</object>
</annotation>
