<annotation>
	<folder>data5</folder>
	<filename>DJI_0004_036.tif</filename>
	<path>C:\Users\IRH\OneDrive - USU\Desktop\windows_v1.8.0\data5\DJI_0004_036.tif</path>
	<source>
		<database>Unknown</database>
	</source>
	<size>
		<width>512</width>
		<height>512</height>
		<depth>3</depth>
	</size>
	<segmented>0</segmented>
	<object>
		<name>vc</name>
		<pose>Unspecified</pose>
		<truncated>0</truncated>
		<difficult>0</difficult>
		<bndbox>
			<xmin>33</xmin>
			<ymin>355</ymin>
			<xmax>56</xmax>
			<ymax>377</ymax>
		</bndbox>
	</object>
	<object>
		<name>vc</name>
		<pose>Unspecified</pose>
		<truncated>0</truncated>
		<difficult>0</difficult>
		<bndbox>
			<xmin>37</xmin>
			<ymin>405</ymin>
			<xmax>61</xmax>
			<ymax>425</ymax>
		</bndbox>
	</object>
	<object>
		<name>vc</name>
		<pose>Unspecified</pose>
		<truncated>0</truncated>
		<difficult>0</difficult>
		<bndbox>
			<xmin>41</xmin>
			<ymin>483</ymin>
			<xmax>61</xmax>
			<ymax>503</ymax>
		</bndbox>
	</object>
	<object>
		<name>vc</name>
		<pose>Unspecified</pose>
		<truncated>0</truncated>
		<difficult>0</difficult>
		<bndbox>
			<xmin>221</xmin>
			<ymin>66</ymin>
			<xmax>239</xmax>
			<ymax>84</ymax>
		</bndbox>
	</object>
	<object>
		<name>vc</name>
		<pose>Unspecified</pose>
		<truncated>0</truncated>
		<difficult>0</difficult>
		<bndbox>
			<xmin>403</xmin>
			<ymin>134</ymin>
			<xmax>428</xmax>
			<ymax>168</ymax>
		</bndbox>
	</object>
	<object>
		<name>vc</name>
		<pose>Unspecified</pose>
		<truncated>0</truncated>
		<difficult>0</difficult>
		<bndbox>
			<xmin>220</xmin>
			<ymin>258</ymin>
			<xmax>241</xmax>
			<ymax>287</ymax>
		</bndbox>
	</object>
	<object>
		<name>vc</name>
		<pose>Unspecified</pose>
		<truncated>0</truncated>
		<difficult>0</difficult>
		<bndbox>
			<xmin>409</xmin>
			<ymin>281</ymin>
			<xmax>425</xmax>
			<ymax>303</ymax>
		</bndbox>
	</object>
	<object>
		<name>vc</name>
		<pose>Unspecified</pose>
		<truncated>0</truncated>
		<difficult>0</difficult>
		<bndbox>
			<xmin>406</xmin>
			<ymin>239</ymin>
			<xmax>424</xmax>
			<ymax>265</ymax>
		</bndbox>
	</object>
</annotation>
