<annotation>
	<folder>data5</folder>
	<filename>DJI_0004_018.tif</filename>
	<path>C:\Users\IRH\OneDrive - USU\Desktop\windows_v1.8.0\data5\DJI_0004_018.tif</path>
	<source>
		<database>Unknown</database>
	</source>
	<size>
		<width>512</width>
		<height>512</height>
		<depth>3</depth>
	</size>
	<segmented>0</segmented>
	<object>
		<name>vc</name>
		<pose>Unspecified</pose>
		<truncated>1</truncated>
		<difficult>0</difficult>
		<bndbox>
			<xmin>119</xmin>
			<ymin>1</ymin>
			<xmax>144</xmax>
			<ymax>33</ymax>
		</bndbox>
	</object>
	<object>
		<name>vc</name>
		<pose>Unspecified</pose>
		<truncated>0</truncated>
		<difficult>0</difficult>
		<bndbox>
			<xmin>116</xmin>
			<ymin>45</ymin>
			<xmax>143</xmax>
			<ymax>70</ymax>
		</bndbox>
	</object>
	<object>
		<name>vc</name>
		<pose>Unspecified</pose>
		<truncated>0</truncated>
		<difficult>0</difficult>
		<bndbox>
			<xmin>120</xmin>
			<ymin>97</ymin>
			<xmax>143</xmax>
			<ymax>131</ymax>
		</bndbox>
	</object>
	<object>
		<name>vc</name>
		<pose>Unspecified</pose>
		<truncated>0</truncated>
		<difficult>0</difficult>
		<bndbox>
			<xmin>121</xmin>
			<ymin>137</ymin>
			<xmax>144</xmax>
			<ymax>183</ymax>
		</bndbox>
	</object>
	<object>
		<name>vc</name>
		<pose>Unspecified</pose>
		<truncated>0</truncated>
		<difficult>0</difficult>
		<bndbox>
			<xmin>120</xmin>
			<ymin>233</ymin>
			<xmax>146</xmax>
			<ymax>257</ymax>
		</bndbox>
	</object>
	<object>
		<name>vc</name>
		<pose>Unspecified</pose>
		<truncated>0</truncated>
		<difficult>0</difficult>
		<bndbox>
			<xmin>126</xmin>
			<ymin>285</ymin>
			<xmax>149</xmax>
			<ymax>310</ymax>
		</bndbox>
	</object>
	<object>
		<name>vc</name>
		<pose>Unspecified</pose>
		<truncated>0</truncated>
		<difficult>0</difficult>
		<bndbox>
			<xmin>119</xmin>
			<ymin>343</ymin>
			<xmax>148</xmax>
			<ymax>391</ymax>
		</bndbox>
	</object>
	<object>
		<name>vc</name>
		<pose>Unspecified</pose>
		<truncated>0</truncated>
		<difficult>0</difficult>
		<bndbox>
			<xmin>125</xmin>
			<ymin>399</ymin>
			<xmax>150</xmax>
			<ymax>469</ymax>
		</bndbox>
	</object>
</annotation>
