<annotation>
	<folder>data4</folder>
	<filename>DJI_0034_053.tif</filename>
	<path>C:\Users\IRH\OneDrive - USU\Desktop\windows_v1.8.0\data4\DJI_0034_053.tif</path>
	<source>
		<database>Unknown</database>
	</source>
	<size>
		<width>512</width>
		<height>512</height>
		<depth>3</depth>
	</size>
	<segmented>0</segmented>
	<object>
		<name>vc</name>
		<pose>Unspecified</pose>
		<truncated>0</truncated>
		<difficult>0</difficult>
		<bndbox>
			<xmin>296</xmin>
			<ymin>107</ymin>
			<xmax>321</xmax>
			<ymax>128</ymax>
		</bndbox>
	</object>
	<object>
		<name>vc</name>
		<pose>Unspecified</pose>
		<truncated>0</truncated>
		<difficult>0</difficult>
		<bndbox>
			<xmin>304</xmin>
			<ymin>34</ymin>
			<xmax>323</xmax>
			<ymax>47</ymax>
		</bndbox>
	</object>
	<object>
		<name>vc</name>
		<pose>Unspecified</pose>
		<truncated>0</truncated>
		<difficult>0</difficult>
		<bndbox>
			<xmin>287</xmin>
			<ymin>345</ymin>
			<xmax>306</xmax>
			<ymax>359</ymax>
		</bndbox>
	</object>
	<object>
		<name>vc</name>
		<pose>Unspecified</pose>
		<truncated>0</truncated>
		<difficult>0</difficult>
		<bndbox>
			<xmin>472</xmin>
			<ymin>28</ymin>
			<xmax>495</xmax>
			<ymax>103</ymax>
		</bndbox>
	</object>
	<object>
		<name>vc</name>
		<pose>Unspecified</pose>
		<truncated>0</truncated>
		<difficult>0</difficult>
		<bndbox>
			<xmin>465</xmin>
			<ymin>227</ymin>
			<xmax>492</xmax>
			<ymax>248</ymax>
		</bndbox>
	</object>
	<object>
		<name>vc</name>
		<pose>Unspecified</pose>
		<truncated>0</truncated>
		<difficult>0</difficult>
		<bndbox>
			<xmin>294</xmin>
			<ymin>183</ymin>
			<xmax>316</xmax>
			<ymax>199</ymax>
		</bndbox>
	</object>
	<object>
		<name>vc</name>
		<pose>Unspecified</pose>
		<truncated>0</truncated>
		<difficult>0</difficult>
		<bndbox>
			<xmin>467</xmin>
			<ymin>261</ymin>
			<xmax>489</xmax>
			<ymax>279</ymax>
		</bndbox>
	</object>
	<object>
		<name>vc</name>
		<pose>Unspecified</pose>
		<truncated>0</truncated>
		<difficult>0</difficult>
		<bndbox>
			<xmin>464</xmin>
			<ymin>287</ymin>
			<xmax>486</xmax>
			<ymax>348</ymax>
		</bndbox>
	</object>
	<object>
		<name>vc</name>
		<pose>Unspecified</pose>
		<truncated>0</truncated>
		<difficult>0</difficult>
		<bndbox>
			<xmin>120</xmin>
			<ymin>97</ymin>
			<xmax>138</xmax>
			<ymax>110</ymax>
		</bndbox>
	</object>
	<object>
		<name>vc</name>
		<pose>Unspecified</pose>
		<truncated>0</truncated>
		<difficult>0</difficult>
		<bndbox>
			<xmin>449</xmin>
			<ymin>494</ymin>
			<xmax>470</xmax>
			<ymax>508</ymax>
		</bndbox>
	</object>
</annotation>
